tree_sitter_arduino/__init__.py
tree_sitter_arduino/__init__.pyi
tree_sitter_arduino/_binding.abi3.so
tree_sitter_arduino/binding.c
tree_sitter_arduino/py.typed
tree_sitter_arduino/queries/highlights.scm
tree_sitter_arduino/queries/tags.scm
tree_sitter_arduino-0.24.0.dist-info/METADATA
tree_sitter_arduino-0.24.0.dist-info/WHEEL
tree_sitter_arduino-0.24.0.dist-info/top_level.txt
tree_sitter_arduino-0.24.0.dist-info/RECORD
tree_sitter_arduino-0.24.0.dist-info/licenses/LICENSE
