Metadata-Version: 2.4
Name: tree-sitter-arduino
Version: 0.24.0
Summary: Arduino grammar for tree-sitter
Author-email: ObserverOfTime <chronobserver@disroot.org>
License: MIT
Project-URL: Homepage, https://github.com/tree-sitter-grammars/tree-sitter-arduino
Project-URL: Funding, https://github.com/sponsors/ObserverOfTime
Keywords: incremental,parsing,tree-sitter,arduino
Classifier: Intended Audience :: Developers
Classifier: Topic :: Software Development :: Compilers
Classifier: Topic :: Text Processing :: Linguistic
Classifier: Typing :: Typed
Requires-Python: >=3.10
License-File: LICENSE
Provides-Extra: core
Requires-Dist: tree-sitter~=0.25; extra == "core"
Dynamic: license-file
